scrapenhl/__init__.py
scrapenhl-0.1.dist-info/DESCRIPTION.rst
scrapenhl-0.1.dist-info/METADATA
scrapenhl-0.1.dist-info/RECORD
scrapenhl-0.1.dist-info/WHEEL
scrapenhl-0.1.dist-info/metadata.json
scrapenhl-0.1.dist-info/top_level.txt
