Metadata-Version: 2.0
Name: scrapenhl
Version: 0.1
Summary: Scraping and manipulating NHL PbP data
Home-page: https://github.com/muneebalam/scrapenhl
Author: Muneeb Alam
Author-email: muneeb.alam@gmail.com
License: MIT
Platform: UNKNOWN
Requires-Dist: feather-format
Requires-Dist: matplotlib
Requires-Dist: numpy
Requires-Dist: pandas
Requires-Dist: scikit-learn
Requires-Dist: scipy
Requires-Dist: seaborn
